twitchaio/__init__.py
twitchaio/api.py
twitchaio/auth.py
twitchaio/chat.py
twitchaio/commands.py
twitchaio/data.py
twitchaio/emotes.py
twitchaio/events.py
twitchaio/tags.py
twitchaio/utils.py
TwitchAIO-0.5.post0.dist-info/LICENSE
TwitchAIO-0.5.post0.dist-info/METADATA
TwitchAIO-0.5.post0.dist-info/WHEEL
TwitchAIO-0.5.post0.dist-info/top_level.txt
TwitchAIO-0.5.post0.dist-info/RECORD
