Metadata-Version: 2.1
Name: TwitchAIO
Version: 0.5.post0
Summary: Asynchronous Twitch API interface
Author: jespk77
Maintainer: jespk77
License: MIT License
Project-URL: home, https://github.com/jespk77/twitchaio
Keywords: twitch,asynchronous,twitch chat,twitch api
Classifier: Development Status :: 4 - Beta
Classifier: Programming Language :: Python :: 3
Classifier: Programming Language :: Python :: 3.9
Requires-Python: >=3.9
License-File: LICENSE
Requires-Dist: aiohttp >=3.9
Requires-Dist: websockets >=12.0
